README.rst
setup.py
gedcom/__init__.py
gedcom/_version.py
gedcompy.egg-info/PKG-INFO
gedcompy.egg-info/SOURCES.txt
gedcompy.egg-info/dependency_links.txt
gedcompy.egg-info/top_level.txt