Metadata-Version: 1.1
Name: gedcompy
Version: 0.2.6
Summary: Parse and create GEDCOM (geneology) files
Home-page: UNKNOWN
Author: Rory McCann
Author-email: rory@technomancy.org
License: GPLv3+
Platform: UNKNOWN
Classifier: Programming Language :: Python :: 2.5
Classifier: Programming Language :: Python :: 2.6
Classifier: Programming Language :: Python :: 2.7
Classifier: Programming Language :: Python :: 3.3
Classifier: License :: OSI Approved :: GNU General Public License v3 or later (GPLv3+)
Classifier: Intended Audience :: Developers
Classifier: Development Status :: 4 - Beta
Classifier: Topic :: Sociology :: Genealogy
Classifier: Topic :: Sociology :: History
Classifier: Topic :: Text Processing
